embeddinghub
